{
	"format_version": "1.8.0",
	"animations": {
		"idle": {
			"loop": true,
			"animation_length": 2,
			"bones": {
				"head": {
					"rotation": {
						"0.0": {
							"vector": [0, 0, 0]
						},
						"1.0": {
							"vector": [0, 0, 0]
						},
						"2.0": {
							"vector": [0, 0, 0]
						}
					},
					"position": {
						"0.0": {
							"vector": [0, 0, 0]
						},
						"1.0": {
							"vector": [0, -0.5, 0]
						},
						"2.0": {
							"vector": [0, 0, 0]
						}
					}
				},
				"torso": {
					"position": {
						"0.0": {
							"vector": [0, 0, 0]
						},
						"1.0": {
							"vector": [0, -0.5, 0]
						},
						"2.0": {
							"vector": [0, 0, 0]
						}
					}
				},
				"right_arm": {
					"rotation": {
						"0.0": {
							"vector": [-143, -28, 70]
						},
						"1.0": {
							"vector": [-143, -28, 70]
						},
						"2.0": {
							"vector": [-143, -28, 70]
						}
					},
					"position": {
						"0.0": {
							"vector": [-0.75, -3.85, -1]
						},
						"1.0": {
							"vector": [-0.75, -4.35, -1]
						},
						"2.0": {
							"vector": [-0.75, -3.85, -1]
						}
					}
				},
				"left_arm": {
					"rotation": {
						"0.0": {
							"vector": [-148, 7, -77]
						},
						"1.0": {
							"vector": [-148, 7, -77]
						},
						"2.0": {
							"vector": [-148, 7, -77]
						}
					},
					"position": {
						"0.0": {
							"vector": [0, -2.35, -2.25]
						},
						"1.0": {
							"vector": [0, -2.85, -2.25]
						},
						"2.0": {
							"vector": [0, -2.35, -2.25]
						}
					}
				},
				"right_leg": {
					"rotation": {
						"0.0": {
							"vector": [-1, 27, -2]
						},
						"1.0": {
							"vector": [-1, 27, -2]
						},
						"2.0": {
							"vector": [-1, 27, -2]
						}
					}
				},
				"left_leg": {
					"rotation": {
						"0.0": {
							"vector": [0, -40, 0]
						},
						"1.0": {
							"vector": [0, -40, 0]
						},
						"2.0": {
							"vector": [0, -40, 0]
						}
					}
				}
			}
		},
		"punch_right": {
			"animation_length": 0.75,
			"bones": {
				"head": {
					"rotation": {
						"0.0": {
							"vector": [14, 24, -2],
							"easing": "linear"
						},
						"0.0833": {
							"vector": [21, 14, -10],
							"easing": "easeInSine"
						},
						"0.125": {
							"vector": [0, -15, -2],
							"easing": "easeOutCubic"
						}
					},
					"position": {
						"0.0": {
							"vector": [1.75, -0.75, -2.5],
							"easing": "linear"
						},
						"0.0833": {
							"vector": [-2, -1, -4],
							"easing": "easeInSine"
						},
						"0.125": {
							"vector": [-0.75, -0.75, 0],
							"easing": "easeOutCubic"
						}
					}
				},
				"torso": {
					"rotation": {
						"0.0": {
							"vector": [27, 30, 10],
							"easing": "linear"
						},
						"0.0833": {
							"vector": [21, 44, -4],
							"easing": "easeInSine"
						},
						"0.125": {
							"vector": [5, -30, -4],
							"easing": "easeOutCubic"
						}
					},
					"position": {
						"0.0": {
							"vector": [1.75, -1, -2],
							"easing": "linear"
						},
						"0.0833": {
							"vector": [-2, -1, -4],
							"easing": "easeInSine"
						},
						"0.125": {
							"vector": [0, -1, 0],
							"easing": "easeOutCubic"
						}
					}
				},
				"right_arm": {
					"rotation": {
						"0.0": {
							"vector": [-23.10498, -1.95677, 26.31639],
							"easing": "linear"
						},
						"0.0833": {
							"vector": [-102, 75, -32],
							"easing": "easeInSine"
						},
						"0.125": {
							"vector": [-87, -8, 0],
							"easing": "easeOutCubic"
						}
					},
					"position": {
						"0.0": {
							"vector": [2, -2, 5],
							"easing": "linear"
						},
						"0.0833": {
							"vector": [2, -2, 3],
							"easing": "easeInSine"
						},
						"0.125": {
							"vector": [0.25, -0.75, -6],
							"easing": "easeOutCubic"
						}
					}
				},
				"left_arm": {
					"rotation": {
						"0.0": {
							"vector": [-50, 19, 13],
							"easing": "linear"
						},
						"0.0833": {
							"vector": [-39, -12, -16],
							"easing": "easeInSine"
						},
						"0.125": {
							"vector": [0, -69, -45],
							"easing": "easeOutCubic"
						}
					},
					"position": {
						"0.0": {
							"vector": [1.75, -1.5, -5.75],
							"easing": "linear"
						},
						"0.0833": {
							"vector": [-2.5, -1.5, -9.75],
							"easing": "easeInSine"
						},
						"0.125": {
							"vector": [-2.5, -1.5, 5.25],
							"easing": "easeOutCubic"
						}
					}
				},
				"right_leg": {
					"rotation": {
						"0.0": {
							"vector": [24, 34, 14],
							"easing": "linear"
						},
						"0.0833": {
							"vector": [32, 25, 14],
							"easing": "easeInSine"
						}
					},
					"position": {
						"0.0": {
							"vector": [0, 0, 3],
							"easing": "linear"
						},
						"0.0833": {
							"vector": [0, 0, 3],
							"easing": "easeInSine"
						},
						"0.125": {
							"vector": [-1.5, 0, 2.75],
							"easing": "easeOutCubic"
						}
					}
				},
				"left_leg": {
					"rotation": {
						"vector": ["linear", "linear", "linear"]
					},
					"position": {
						"0.0": {
							"vector": [1, 0, -2],
							"easing": "linear"
						},
						"0.0833": {
							"vector": [1, 0, -2.75],
							"easing": "easeInSine"
						},
						"0.125": {
							"vector": [1, 0, -3.25],
							"easing": "easeOutCubic"
						}
					}
				},
				"boobies": {
					"position": {
						"0.0": {
							"vector": [0, 0, 0]
						},
						"0.0833": {
							"vector": [0, 0.5, -0.25],
							"easing": "easeOutBack",
							"easingArgs": [3]
						},
						"0.25": {
							"vector": [0, 0, 0],
							"easing": "easeOutBack",
							"easingArgs": [3]
						},
						"0.375": {
							"vector": [0, 0.25, -0.15],
							"easing": "easeOutBack",
							"easingArgs": [3]
						},
						"0.5417": {
							"vector": [0, 0, 0],
							"easing": "easeOutBack",
							"easingArgs": [3]
						}
					}
				}
			}
		},
		"punch_left": {
			"animation_length": 0.7917,
			"bones": {
				"head": {
					"rotation": {
						"0.0": {
							"vector": [14, -24, 2],
							"easing": "linear"
						},
						"0.0833": {
							"vector": [21, -14, 10],
							"easing": "easeInSine"
						},
						"0.125": {
							"vector": [0, 15, 2],
							"easing": "easeOutCubic"
						}
					},
					"position": {
						"0.0": {
							"vector": [-1.75, -0.75, -2.5],
							"easing": "linear"
						},
						"0.0833": {
							"vector": [2, -1, -4],
							"easing": "easeInSine"
						},
						"0.125": {
							"vector": [0.75, -0.75, 0],
							"easing": "easeOutCubic"
						}
					}
				},
				"torso": {
					"rotation": {
						"0.0": {
							"vector": [27, -30, -10],
							"easing": "linear"
						},
						"0.0833": {
							"vector": [21, -44, 4],
							"easing": "easeInSine"
						},
						"0.125": {
							"vector": [5, 30, 4],
							"easing": "easeOutCubic"
						}
					},
					"position": {
						"0.0": {
							"vector": [-1.75, -1, -2],
							"easing": "linear"
						},
						"0.0833": {
							"vector": [2, -1, -4],
							"easing": "easeInSine"
						},
						"0.125": {
							"vector": [0, -1, 0],
							"easing": "easeOutCubic"
						}
					}
				},
				"right_arm": {
					"rotation": {
						"0.0": {
							"vector": [-50, -19, -13],
							"easing": "linear"
						},
						"0.0833": {
							"vector": [-39, 12, 16],
							"easing": "easeInSine"
						},
						"0.125": {
							"vector": [0, 69, 45],
							"easing": "easeOutCubic"
						}
					},
					"position": {
						"0.0": {
							"vector": [-1.75, -1.5, -5.75],
							"easing": "linear"
						},
						"0.0833": {
							"vector": [2.5, -1.5, -9.75],
							"easing": "easeInSine"
						},
						"0.125": {
							"vector": [2.5, -1.5, 5.25],
							"easing": "easeOutCubic"
						}
					}
				},
				"left_arm": {
					"rotation": {
						"0.0": {
							"vector": [-23.10498, 1.95677, -26.31639],
							"easing": "linear"
						},
						"0.0833": {
							"vector": [-102, -75, 32],
							"easing": "easeInSine"
						},
						"0.125": {
							"vector": [-87, 8, 0],
							"easing": "easeOutCubic"
						}
					},
					"position": {
						"0.0": {
							"vector": [-2, -2, 5],
							"easing": "linear"
						},
						"0.0833": {
							"vector": [-2, -2, 3],
							"easing": "easeInSine"
						},
						"0.125": {
							"vector": [-0.25, -0.75, -6],
							"easing": "easeOutCubic"
						}
					}
				},
				"right_leg": {
					"position": {
						"0.0": {
							"vector": [-1, 0, -2],
							"easing": "linear"
						},
						"0.0833": {
							"vector": [-1, 0, -2.75],
							"easing": "easeInSine"
						},
						"0.125": {
							"vector": [-1, 0, -3.25],
							"easing": "easeOutCubic"
						}
					}
				},
				"left_leg": {
					"rotation": {
						"vector": ["linear", "linear", "linear"]
					},
					"position": {
						"0.0": {
							"vector": [0, 0, 3],
							"easing": "linear"
						},
						"0.0833": {
							"vector": [0, 0, 3],
							"easing": "easeInSine"
						},
						"0.125": {
							"vector": [1.5, 0, 2.75],
							"easing": "easeOutCubic"
						}
					}
				},
				"boobies": {
					"position": {
						"0.0": {
							"vector": [0, 0, 0]
						},
						"0.0833": {
							"vector": [0, 0.5, -0.25],
							"easing": "easeOutBack",
							"easingArgs": [3]
						},
						"0.25": {
							"vector": [0, 0, 0],
							"easing": "easeOutBack",
							"easingArgs": [3]
						},
						"0.375": {
							"vector": [0, 0.25, -0.15],
							"easing": "easeOutBack",
							"easingArgs": [3]
						},
						"0.5417": {
							"vector": [0, 0, 0],
							"easing": "easeOutBack",
							"easingArgs": [3]
						}
					}
				}
			}
		},
		"sonic_clap": {
			"animation_length": 1.0833,
			"bones": {
				"head": {
					"rotation": {
						"0.0": {
							"vector": [14, -24, 2]
						},
						"0.375": {
							"vector": [-29.5, -4, -6.5],
							"easing": "easeOutCubic"
						},
						"0.4583": {
							"vector": [-0.5, 5, 2],
							"easing": "easeOutQuad"
						}
					},
					"position": {
						"0.0": {
							"vector": [0.25, 1, -2.5]
						},
						"0.375": {
							"vector": [-1, -0.25, 3.75],
							"easing": "easeOutCubic"
						},
						"0.4583": {
							"vector": [1, 0, -4.5],
							"easing": "easeOutQuad"
						}
					}
				},
				"torso": {
					"rotation": {
						"0.0": {
							"vector": [8.99793, -16.80798, 1.25671]
						},
						"0.375": {
							"vector": [-29.5, -4, -6.5],
							"easing": "easeOutCubic"
						},
						"0.4583": {
							"vector": [27, 5, 2],
							"easing": "easeOutQuad"
						}
					},
					"position": {
						"0.0": {
							"vector": [-0.25, 0.25, -2]
						},
						"0.375": {
							"vector": [-1, -0.25, 3.75],
							"easing": "easeOutCubic"
						},
						"0.4583": {
							"vector": [1, 0, -4.5],
							"easing": "easeOutQuad"
						}
					}
				},
				"right_arm": {
					"rotation": {
						"0.0": {
							"vector": [-25.47201, -2.74829, 27.17046]
						},
						"0.375": {
							"vector": [-101.5, 77, -11],
							"easing": "easeOutCubic"
						},
						"0.4583": {
							"vector": [-82.2588, -22.45591, -0.7053],
							"easing": "easeOutQuad"
						}
					},
					"position": {
						"0.0": {
							"vector": [-1.75, -1.5, -3.75]
						},
						"0.375": {
							"vector": [-1.75, -1.5, -3.75],
							"easing": "easeOutCubic"
						},
						"0.4583": {
							"vector": [1, 0, -7.25],
							"easing": "easeOutQuad"
						}
					}
				},
				"left_arm": {
					"rotation": {
						"0.0": {
							"vector": [-22.68797, -4.8972, -42.43333]
						},
						"0.375": {
							"vector": [18, -12, -101],
							"easing": "easeOutCubic"
						},
						"0.4583": {
							"vector": [-85, 17.5, 1.5],
							"easing": "easeOutQuad"
						}
					},
					"position": {
						"0.0": {
							"vector": [1, -1.5, 0]
						},
						"0.375": {
							"vector": [2.35, -1.5, 2.75],
							"easing": "easeOutCubic"
						},
						"0.4583": {
							"vector": [-0.25, -0.5, -7.5],
							"easing": "easeOutQuad"
						}
					}
				},
				"right_leg": {
					"rotation": {
						"0.0": {
							"vector": [2.6, -2.3, -2]
						},
						"0.375": {
							"vector": [2.27765, -2.6196, 5.50012],
							"easing": "easeOutCubic"
						}
					},
					"position": {
						"0.0": {
							"vector": [-1, 0, -2]
						},
						"0.375": {
							"vector": [-1, 0, -2.75],
							"easing": "easeOutCubic"
						},
						"0.4583": {
							"vector": [-1, 0, -4],
							"easing": "easeOutQuad"
						}
					}
				},
				"left_leg": {
					"rotation": {
						"vector": [17, -22, -10]
					},
					"position": {
						"0.0": {
							"vector": [0, 0, 2]
						},
						"0.375": {
							"vector": [0, 0, -0.5],
							"easing": "easeOutCubic"
						},
						"0.4583": {
							"vector": [1.5, 0, 2],
							"easing": "easeOutQuad"
						}
					}
				}
			}
		},
		"barrage": {
			"animation_length": 3.0417,
			"bones": {
				"head": {
					"rotation": {
						"0.0": {
							"vector": [14, 24, -2],
							"easing": "linear"
						},
						"0.0833": {
							"vector": [21, 14, -10],
							"easing": "easeInSine"
						},
						"0.125": {
							"vector": [0, -15, -2],
							"easing": "easeOutCubic"
						},
						"0.1667": {
							"vector": [0, -15, -2],
							"easing": "easeOutCubic"
						},
						"0.25": {
							"vector": [14, -24, 2],
							"easing": "linear"
						},
						"0.3333": {
							"vector": [21, -14, 10],
							"easing": "easeInSine"
						},
						"0.375": {
							"vector": [0, 15, 2],
							"easing": "easeOutCubic"
						},
						"0.4167": {
							"vector": [0, 15, 2],
							"easing": "easeOutCubic"
						},
						"0.5": {
							"vector": [14, 24, -2],
							"easing": "linear"
						},
						"0.5833": {
							"vector": [21, 14, -10],
							"easing": "easeInSine"
						},
						"0.625": {
							"vector": [0, -15, -2],
							"easing": "easeOutCubic"
						},
						"0.6667": {
							"vector": [0, -15, -2],
							"easing": "easeOutCubic"
						},
						"0.75": {
							"vector": [14, -24, 2],
							"easing": "linear"
						},
						"0.8333": {
							"vector": [21, -14, 10],
							"easing": "easeInSine"
						},
						"0.875": {
							"vector": [0, 15, 2],
							"easing": "easeOutCubic"
						},
						"0.9167": {
							"vector": [0, 15, 2],
							"easing": "easeOutCubic"
						},
						"1.0": {
							"vector": [14, 24, -2],
							"easing": "linear"
						},
						"1.0833": {
							"vector": [21, 14, -10],
							"easing": "easeInSine"
						},
						"1.125": {
							"vector": [0, -15, -2],
							"easing": "easeOutCubic"
						},
						"1.1667": {
							"vector": [0, -15, -2],
							"easing": "easeOutCubic"
						},
						"1.25": {
							"vector": [14, -24, 2],
							"easing": "linear"
						},
						"1.3333": {
							"vector": [21, -14, 10],
							"easing": "easeInSine"
						},
						"1.375": {
							"vector": [0, 15, 2],
							"easing": "easeOutCubic"
						},
						"1.4167": {
							"vector": [0, 15, 2],
							"easing": "easeOutCubic"
						},
						"1.5": {
							"vector": [14, 24, -2],
							"easing": "linear"
						},
						"1.5833": {
							"vector": [21, 14, -10],
							"easing": "easeInSine"
						},
						"1.625": {
							"vector": [0, -15, -2],
							"easing": "easeOutCubic"
						},
						"1.6667": {
							"vector": [0, -15, -2],
							"easing": "easeOutCubic"
						},
						"1.75": {
							"vector": [14, -24, 2],
							"easing": "linear"
						},
						"1.8333": {
							"vector": [21, -14, 10],
							"easing": "easeInSine"
						},
						"1.875": {
							"vector": [0, 15, 2],
							"easing": "easeOutCubic"
						},
						"1.9167": {
							"vector": [0, 15, 2],
							"easing": "easeOutCubic"
						},
						"2.0": {
							"vector": [14, 24, -2],
							"easing": "linear"
						},
						"2.0833": {
							"vector": [21, 14, -10],
							"easing": "easeInSine"
						},
						"2.125": {
							"vector": [0, -15, -2],
							"easing": "easeOutCubic"
						},
						"2.1667": {
							"vector": [0, -15, -2],
							"easing": "easeOutCubic"
						},
						"2.25": {
							"vector": [14, -24, 2],
							"easing": "linear"
						},
						"2.3333": {
							"vector": [21, -14, 10],
							"easing": "easeInSine"
						},
						"2.375": {
							"vector": [0, 15, 2],
							"easing": "easeOutCubic"
						},
						"2.4167": {
							"vector": [0, 15, 2],
							"easing": "easeOutCubic"
						},
						"2.5": {
							"vector": [14, 24, -2],
							"easing": "linear"
						},
						"2.5833": {
							"vector": [21, 14, -10],
							"easing": "easeInSine"
						},
						"2.625": {
							"vector": [0, -15, -2],
							"easing": "easeOutCubic"
						},
						"2.6667": {
							"vector": [0, -15, -2],
							"easing": "easeOutCubic"
						}
					},
					"position": {
						"0.0": {
							"vector": [1.75, -0.75, -2.5],
							"easing": "linear"
						},
						"0.0833": {
							"vector": [-2, -1, -4],
							"easing": "easeInSine"
						},
						"0.125": {
							"vector": [-0.75, -0.75, 0],
							"easing": "easeOutCubic"
						},
						"0.1667": {
							"vector": [-0.75, -0.75, 0],
							"easing": "easeOutCubic"
						},
						"0.25": {
							"vector": [-1.75, -0.75, -2.5],
							"easing": "linear"
						},
						"0.3333": {
							"vector": [2, -1, -4],
							"easing": "easeInSine"
						},
						"0.375": {
							"vector": [0.75, -0.75, 0],
							"easing": "easeOutCubic"
						},
						"0.4167": {
							"vector": [0.75, -0.75, 0],
							"easing": "easeOutCubic"
						},
						"0.5": {
							"vector": [1.75, -0.75, -2.5],
							"easing": "linear"
						},
						"0.5833": {
							"vector": [-2, -1, -4],
							"easing": "easeInSine"
						},
						"0.625": {
							"vector": [-0.75, -0.75, 0],
							"easing": "easeOutCubic"
						},
						"0.6667": {
							"vector": [-0.75, -0.75, 0],
							"easing": "easeOutCubic"
						},
						"0.75": {
							"vector": [-1.75, -0.75, -2.5],
							"easing": "linear"
						},
						"0.8333": {
							"vector": [2, -1, -4],
							"easing": "easeInSine"
						},
						"0.875": {
							"vector": [0.75, -0.75, 0],
							"easing": "easeOutCubic"
						},
						"0.9167": {
							"vector": [0.75, -0.75, 0],
							"easing": "easeOutCubic"
						},
						"1.0": {
							"vector": [1.75, -0.75, -2.5],
							"easing": "linear"
						},
						"1.0833": {
							"vector": [-2, -1, -4],
							"easing": "easeInSine"
						},
						"1.125": {
							"vector": [-0.75, -0.75, 0],
							"easing": "easeOutCubic"
						},
						"1.1667": {
							"vector": [-0.75, -0.75, 0],
							"easing": "easeOutCubic"
						},
						"1.25": {
							"vector": [-1.75, -0.75, -2.5],
							"easing": "linear"
						},
						"1.3333": {
							"vector": [2, -1, -4],
							"easing": "easeInSine"
						},
						"1.375": {
							"vector": [0.75, -0.75, 0],
							"easing": "easeOutCubic"
						},
						"1.4167": {
							"vector": [0.75, -0.75, 0],
							"easing": "easeOutCubic"
						},
						"1.5": {
							"vector": [1.75, -0.75, -2.5],
							"easing": "linear"
						},
						"1.5833": {
							"vector": [-2, -1, -4],
							"easing": "easeInSine"
						},
						"1.625": {
							"vector": [-0.75, -0.75, 0],
							"easing": "easeOutCubic"
						},
						"1.6667": {
							"vector": [-0.75, -0.75, 0],
							"easing": "easeOutCubic"
						},
						"1.75": {
							"vector": [-1.75, -0.75, -2.5],
							"easing": "linear"
						},
						"1.8333": {
							"vector": [2, -1, -4],
							"easing": "easeInSine"
						},
						"1.875": {
							"vector": [0.75, -0.75, 0],
							"easing": "easeOutCubic"
						},
						"1.9167": {
							"vector": [0.75, -0.75, 0],
							"easing": "easeOutCubic"
						},
						"2.0": {
							"vector": [1.75, -0.75, -2.5],
							"easing": "linear"
						},
						"2.0833": {
							"vector": [-2, -1, -4],
							"easing": "easeInSine"
						},
						"2.125": {
							"vector": [-0.75, -0.75, 0],
							"easing": "easeOutCubic"
						},
						"2.1667": {
							"vector": [-0.75, -0.75, 0],
							"easing": "easeOutCubic"
						},
						"2.25": {
							"vector": [-1.75, -0.75, -2.5],
							"easing": "linear"
						},
						"2.3333": {
							"vector": [2, -1, -4],
							"easing": "easeInSine"
						},
						"2.375": {
							"vector": [0.75, -0.75, 0],
							"easing": "easeOutCubic"
						},
						"2.4167": {
							"vector": [0.75, -0.75, 0],
							"easing": "easeOutCubic"
						},
						"2.5": {
							"vector": [1.75, -0.75, -2.5],
							"easing": "linear"
						},
						"2.5833": {
							"vector": [-2, -1, -4],
							"easing": "easeInSine"
						},
						"2.625": {
							"vector": [-0.75, -0.75, 0],
							"easing": "easeOutCubic"
						},
						"2.6667": {
							"vector": [-0.75, -0.75, 0],
							"easing": "easeOutCubic"
						}
					}
				},
				"torso": {
					"rotation": {
						"0.0": {
							"vector": [27, 30, 10],
							"easing": "linear"
						},
						"0.0833": {
							"vector": [21, 44, -4],
							"easing": "easeInSine"
						},
						"0.125": {
							"vector": [5, -30, -4],
							"easing": "easeOutCubic"
						},
						"0.1667": {
							"vector": [5, -30, -4],
							"easing": "easeOutCubic"
						},
						"0.25": {
							"vector": [27, -30, -10],
							"easing": "linear"
						},
						"0.3333": {
							"vector": [21, -44, 4],
							"easing": "easeInSine"
						},
						"0.375": {
							"vector": [5, 30, 4],
							"easing": "easeOutCubic"
						},
						"0.4167": {
							"vector": [5, 30, 4],
							"easing": "easeOutCubic"
						},
						"0.5": {
							"vector": [27, 30, 10],
							"easing": "linear"
						},
						"0.5833": {
							"vector": [21, 44, -4],
							"easing": "easeInSine"
						},
						"0.625": {
							"vector": [5, -30, -4],
							"easing": "easeOutCubic"
						},
						"0.6667": {
							"vector": [5, -30, -4],
							"easing": "easeOutCubic"
						},
						"0.75": {
							"vector": [27, -30, -10],
							"easing": "linear"
						},
						"0.8333": {
							"vector": [21, -44, 4],
							"easing": "easeInSine"
						},
						"0.875": {
							"vector": [5, 30, 4],
							"easing": "easeOutCubic"
						},
						"0.9167": {
							"vector": [5, 30, 4],
							"easing": "easeOutCubic"
						},
						"1.0": {
							"vector": [27, 30, 10],
							"easing": "linear"
						},
						"1.0833": {
							"vector": [21, 44, -4],
							"easing": "easeInSine"
						},
						"1.125": {
							"vector": [5, -30, -4],
							"easing": "easeOutCubic"
						},
						"1.1667": {
							"vector": [5, -30, -4],
							"easing": "easeOutCubic"
						},
						"1.25": {
							"vector": [27, -30, -10],
							"easing": "linear"
						},
						"1.3333": {
							"vector": [21, -44, 4],
							"easing": "easeInSine"
						},
						"1.375": {
							"vector": [5, 30, 4],
							"easing": "easeOutCubic"
						},
						"1.4167": {
							"vector": [5, 30, 4],
							"easing": "easeOutCubic"
						},
						"1.5": {
							"vector": [27, 30, 10],
							"easing": "linear"
						},
						"1.5833": {
							"vector": [21, 44, -4],
							"easing": "easeInSine"
						},
						"1.625": {
							"vector": [5, -30, -4],
							"easing": "easeOutCubic"
						},
						"1.6667": {
							"vector": [5, -30, -4],
							"easing": "easeOutCubic"
						},
						"1.75": {
							"vector": [27, -30, -10],
							"easing": "linear"
						},
						"1.8333": {
							"vector": [21, -44, 4],
							"easing": "easeInSine"
						},
						"1.875": {
							"vector": [5, 30, 4],
							"easing": "easeOutCubic"
						},
						"1.9167": {
							"vector": [5, 30, 4],
							"easing": "easeOutCubic"
						},
						"2.0": {
							"vector": [27, 30, 10],
							"easing": "linear"
						},
						"2.0833": {
							"vector": [21, 44, -4],
							"easing": "easeInSine"
						},
						"2.125": {
							"vector": [5, -30, -4],
							"easing": "easeOutCubic"
						},
						"2.1667": {
							"vector": [5, -30, -4],
							"easing": "easeOutCubic"
						},
						"2.25": {
							"vector": [27, -30, -10],
							"easing": "linear"
						},
						"2.3333": {
							"vector": [21, -44, 4],
							"easing": "easeInSine"
						},
						"2.375": {
							"vector": [5, 30, 4],
							"easing": "easeOutCubic"
						},
						"2.4167": {
							"vector": [5, 30, 4],
							"easing": "easeOutCubic"
						},
						"2.5": {
							"vector": [27, 30, 10],
							"easing": "linear"
						},
						"2.5833": {
							"vector": [21, 44, -4],
							"easing": "easeInSine"
						},
						"2.625": {
							"vector": [5, -30, -4],
							"easing": "easeOutCubic"
						},
						"2.6667": {
							"vector": [5, -30, -4],
							"easing": "easeOutCubic"
						}
					},
					"position": {
						"0.0": {
							"vector": [1.75, -1, -2],
							"easing": "linear"
						},
						"0.0833": {
							"vector": [-2, -1, -4],
							"easing": "easeInSine"
						},
						"0.125": {
							"vector": [0, -1, 0],
							"easing": "easeOutCubic"
						},
						"0.1667": {
							"vector": [0, -1, 0],
							"easing": "easeOutCubic"
						},
						"0.25": {
							"vector": [-1.75, -1, -2],
							"easing": "linear"
						},
						"0.3333": {
							"vector": [2, -1, -4],
							"easing": "easeInSine"
						},
						"0.375": {
							"vector": [0, -1, 0],
							"easing": "easeOutCubic"
						},
						"0.4167": {
							"vector": [0, -1, 0],
							"easing": "easeOutCubic"
						},
						"0.5": {
							"vector": [1.75, -1, -2],
							"easing": "linear"
						},
						"0.5833": {
							"vector": [-2, -1, -4],
							"easing": "easeInSine"
						},
						"0.625": {
							"vector": [0, -1, 0],
							"easing": "easeOutCubic"
						},
						"0.6667": {
							"vector": [0, -1, 0],
							"easing": "easeOutCubic"
						},
						"0.75": {
							"vector": [-1.75, -1, -2],
							"easing": "linear"
						},
						"0.8333": {
							"vector": [2, -1, -4],
							"easing": "easeInSine"
						},
						"0.875": {
							"vector": [0, -1, 0],
							"easing": "easeOutCubic"
						},
						"0.9167": {
							"vector": [0, -1, 0],
							"easing": "easeOutCubic"
						},
						"1.0": {
							"vector": [1.75, -1, -2],
							"easing": "linear"
						},
						"1.0833": {
							"vector": [-2, -1, -4],
							"easing": "easeInSine"
						},
						"1.125": {
							"vector": [0, -1, 0],
							"easing": "easeOutCubic"
						},
						"1.1667": {
							"vector": [0, -1, 0],
							"easing": "easeOutCubic"
						},
						"1.25": {
							"vector": [-1.75, -1, -2],
							"easing": "linear"
						},
						"1.3333": {
							"vector": [2, -1, -4],
							"easing": "easeInSine"
						},
						"1.375": {
							"vector": [0, -1, 0],
							"easing": "easeOutCubic"
						},
						"1.4167": {
							"vector": [0, -1, 0],
							"easing": "easeOutCubic"
						},
						"1.5": {
							"vector": [1.75, -1, -2],
							"easing": "linear"
						},
						"1.5833": {
							"vector": [-2, -1, -4],
							"easing": "easeInSine"
						},
						"1.625": {
							"vector": [0, -1, 0],
							"easing": "easeOutCubic"
						},
						"1.6667": {
							"vector": [0, -1, 0],
							"easing": "easeOutCubic"
						},
						"1.75": {
							"vector": [-1.75, -1, -2],
							"easing": "linear"
						},
						"1.8333": {
							"vector": [2, -1, -4],
							"easing": "easeInSine"
						},
						"1.875": {
							"vector": [0, -1, 0],
							"easing": "easeOutCubic"
						},
						"1.9167": {
							"vector": [0, -1, 0],
							"easing": "easeOutCubic"
						},
						"2.0": {
							"vector": [1.75, -1, -2],
							"easing": "linear"
						},
						"2.0833": {
							"vector": [-2, -1, -4],
							"easing": "easeInSine"
						},
						"2.125": {
							"vector": [0, -1, 0],
							"easing": "easeOutCubic"
						},
						"2.1667": {
							"vector": [0, -1, 0],
							"easing": "easeOutCubic"
						},
						"2.25": {
							"vector": [-1.75, -1, -2],
							"easing": "linear"
						},
						"2.3333": {
							"vector": [2, -1, -4],
							"easing": "easeInSine"
						},
						"2.375": {
							"vector": [0, -1, 0],
							"easing": "easeOutCubic"
						},
						"2.4167": {
							"vector": [0, -1, 0],
							"easing": "easeOutCubic"
						},
						"2.5": {
							"vector": [1.75, -1, -2],
							"easing": "linear"
						},
						"2.5833": {
							"vector": [-2, -1, -4],
							"easing": "easeInSine"
						},
						"2.625": {
							"vector": [0, -1, 0],
							"easing": "easeOutCubic"
						},
						"2.6667": {
							"vector": [0, -1, 0],
							"easing": "easeOutCubic"
						}
					}
				},
				"right_arm": {
					"rotation": {
						"0.0": {
							"vector": [-23.10498, -1.95677, 26.31639],
							"easing": "linear"
						},
						"0.0833": {
							"vector": [-102, 75, -32],
							"easing": "easeInSine"
						},
						"0.125": {
							"vector": [-87, -8, 0],
							"easing": "easeOutCubic"
						},
						"0.1667": {
							"vector": [-87, -8, 0],
							"easing": "easeOutCubic"
						},
						"0.25": {
							"vector": [-50, -19, -13],
							"easing": "linear"
						},
						"0.3333": {
							"vector": [-39, 12, 16],
							"easing": "easeInSine"
						},
						"0.375": {
							"vector": [0, 69, 45],
							"easing": "easeOutCubic"
						},
						"0.4167": {
							"vector": [0, 69, 45],
							"easing": "easeOutCubic"
						},
						"0.5": {
							"vector": [-23.10498, -1.95677, 26.31639],
							"easing": "linear"
						},
						"0.5833": {
							"vector": [-102, 75, -32],
							"easing": "easeInSine"
						},
						"0.625": {
							"vector": [-87, -8, 0],
							"easing": "easeOutCubic"
						},
						"0.6667": {
							"vector": [-87, -8, 0],
							"easing": "easeOutCubic"
						},
						"0.75": {
							"vector": [-50, -19, -13],
							"easing": "linear"
						},
						"0.8333": {
							"vector": [-39, 12, 16],
							"easing": "easeInSine"
						},
						"0.875": {
							"vector": [0, 69, 45],
							"easing": "easeOutCubic"
						},
						"0.9167": {
							"vector": [0, 69, 45],
							"easing": "easeOutCubic"
						},
						"1.0": {
							"vector": [-23.10498, -1.95677, 26.31639],
							"easing": "linear"
						},
						"1.0833": {
							"vector": [-102, 75, -32],
							"easing": "easeInSine"
						},
						"1.125": {
							"vector": [-87, -8, 0],
							"easing": "easeOutCubic"
						},
						"1.1667": {
							"vector": [-87, -8, 0],
							"easing": "easeOutCubic"
						},
						"1.25": {
							"vector": [-50, -19, -13],
							"easing": "linear"
						},
						"1.3333": {
							"vector": [-39, 12, 16],
							"easing": "easeInSine"
						},
						"1.375": {
							"vector": [0, 69, 45],
							"easing": "easeOutCubic"
						},
						"1.4167": {
							"vector": [0, 69, 45],
							"easing": "easeOutCubic"
						},
						"1.5": {
							"vector": [-23.10498, -1.95677, 26.31639],
							"easing": "linear"
						},
						"1.5833": {
							"vector": [-102, 75, -32],
							"easing": "easeInSine"
						},
						"1.625": {
							"vector": [-87, -8, 0],
							"easing": "easeOutCubic"
						},
						"1.6667": {
							"vector": [-87, -8, 0],
							"easing": "easeOutCubic"
						},
						"1.75": {
							"vector": [-50, -19, -13],
							"easing": "linear"
						},
						"1.8333": {
							"vector": [-39, 12, 16],
							"easing": "easeInSine"
						},
						"1.875": {
							"vector": [0, 69, 45],
							"easing": "easeOutCubic"
						},
						"1.9167": {
							"vector": [0, 69, 45],
							"easing": "easeOutCubic"
						},
						"2.0": {
							"vector": [-23.10498, -1.95677, 26.31639],
							"easing": "linear"
						},
						"2.0833": {
							"vector": [-102, 75, -32],
							"easing": "easeInSine"
						},
						"2.125": {
							"vector": [-87, -8, 0],
							"easing": "easeOutCubic"
						},
						"2.1667": {
							"vector": [-87, -8, 0],
							"easing": "easeOutCubic"
						},
						"2.25": {
							"vector": [-50, -19, -13],
							"easing": "linear"
						},
						"2.3333": {
							"vector": [-39, 12, 16],
							"easing": "easeInSine"
						},
						"2.375": {
							"vector": [0, 69, 45],
							"easing": "easeOutCubic"
						},
						"2.4167": {
							"vector": [0, 69, 45],
							"easing": "easeOutCubic"
						},
						"2.5": {
							"vector": [-23.10498, -1.95677, 26.31639],
							"easing": "linear"
						},
						"2.5833": {
							"vector": [-102, 75, -32],
							"easing": "easeInSine"
						},
						"2.625": {
							"vector": [-87, -8, 0],
							"easing": "easeOutCubic"
						},
						"2.6667": {
							"vector": [-87, -8, 0],
							"easing": "easeOutCubic"
						}
					},
					"position": {
						"0.0": {
							"vector": [2, -2, 5],
							"easing": "linear"
						},
						"0.0833": {
							"vector": [2, -2, 3],
							"easing": "easeInSine"
						},
						"0.125": {
							"vector": [0.25, -0.75, -6],
							"easing": "easeOutCubic"
						},
						"0.1667": {
							"vector": [0.25, -0.75, -6],
							"easing": "easeOutCubic"
						},
						"0.25": {
							"vector": [-1.75, -1.5, -5.75],
							"easing": "linear"
						},
						"0.3333": {
							"vector": [2.5, -1.5, -9.75],
							"easing": "easeInSine"
						},
						"0.375": {
							"vector": [2.5, -1.5, 5.25],
							"easing": "easeOutCubic"
						},
						"0.4167": {
							"vector": [2.5, -1.5, 5.25],
							"easing": "easeOutCubic"
						},
						"0.5": {
							"vector": [2, -2, 5],
							"easing": "linear"
						},
						"0.5833": {
							"vector": [2, -2, 3],
							"easing": "easeInSine"
						},
						"0.625": {
							"vector": [0.25, -0.75, -6],
							"easing": "easeOutCubic"
						},
						"0.6667": {
							"vector": [0.25, -0.75, -6],
							"easing": "easeOutCubic"
						},
						"0.75": {
							"vector": [-1.75, -1.5, -5.75],
							"easing": "linear"
						},
						"0.8333": {
							"vector": [2.5, -1.5, -9.75],
							"easing": "easeInSine"
						},
						"0.875": {
							"vector": [2.5, -1.5, 5.25],
							"easing": "easeOutCubic"
						},
						"0.9167": {
							"vector": [2.5, -1.5, 5.25],
							"easing": "easeOutCubic"
						},
						"1.0": {
							"vector": [2, -2, 5],
							"easing": "linear"
						},
						"1.0833": {
							"vector": [2, -2, 3],
							"easing": "easeInSine"
						},
						"1.125": {
							"vector": [0.25, -0.75, -6],
							"easing": "easeOutCubic"
						},
						"1.1667": {
							"vector": [0.25, -0.75, -6],
							"easing": "easeOutCubic"
						},
						"1.25": {
							"vector": [-1.75, -1.5, -5.75],
							"easing": "linear"
						},
						"1.3333": {
							"vector": [2.5, -1.5, -9.75],
							"easing": "easeInSine"
						},
						"1.375": {
							"vector": [2.5, -1.5, 5.25],
							"easing": "easeOutCubic"
						},
						"1.4167": {
							"vector": [2.5, -1.5, 5.25],
							"easing": "easeOutCubic"
						},
						"1.5": {
							"vector": [2, -2, 5],
							"easing": "linear"
						},
						"1.5833": {
							"vector": [2, -2, 3],
							"easing": "easeInSine"
						},
						"1.625": {
							"vector": [0.25, -0.75, -6],
							"easing": "easeOutCubic"
						},
						"1.6667": {
							"vector": [0.25, -0.75, -6],
							"easing": "easeOutCubic"
						},
						"1.75": {
							"vector": [-1.75, -1.5, -5.75],
							"easing": "linear"
						},
						"1.8333": {
							"vector": [2.5, -1.5, -9.75],
							"easing": "easeInSine"
						},
						"1.875": {
							"vector": [2.5, -1.5, 5.25],
							"easing": "easeOutCubic"
						},
						"1.9167": {
							"vector": [2.5, -1.5, 5.25],
							"easing": "easeOutCubic"
						},
						"2.0": {
							"vector": [2, -2, 5],
							"easing": "linear"
						},
						"2.0833": {
							"vector": [2, -2, 3],
							"easing": "easeInSine"
						},
						"2.125": {
							"vector": [0.25, -0.75, -6],
							"easing": "easeOutCubic"
						},
						"2.1667": {
							"vector": [0.25, -0.75, -6],
							"easing": "easeOutCubic"
						},
						"2.25": {
							"vector": [-1.75, -1.5, -5.75],
							"easing": "linear"
						},
						"2.3333": {
							"vector": [2.5, -1.5, -9.75],
							"easing": "easeInSine"
						},
						"2.375": {
							"vector": [2.5, -1.5, 5.25],
							"easing": "easeOutCubic"
						},
						"2.4167": {
							"vector": [2.5, -1.5, 5.25],
							"easing": "easeOutCubic"
						},
						"2.5": {
							"vector": [2, -2, 5],
							"easing": "linear"
						},
						"2.5833": {
							"vector": [2, -2, 3],
							"easing": "easeInSine"
						},
						"2.625": {
							"vector": [0.25, -0.75, -6],
							"easing": "easeOutCubic"
						},
						"2.6667": {
							"vector": [0.25, -0.75, -6],
							"easing": "easeOutCubic"
						}
					}
				},
				"left_arm": {
					"rotation": {
						"0.0": {
							"vector": [-50, 19, 13],
							"easing": "linear"
						},
						"0.0833": {
							"vector": [-39, -12, -16],
							"easing": "easeInSine"
						},
						"0.125": {
							"vector": [0, -69, -45],
							"easing": "easeOutCubic"
						},
						"0.1667": {
							"vector": [0, -69, -45],
							"easing": "easeOutCubic"
						},
						"0.25": {
							"vector": [-23.10498, 1.95677, -26.31639],
							"easing": "linear"
						},
						"0.3333": {
							"vector": [-102, -75, 32],
							"easing": "easeInSine"
						},
						"0.375": {
							"vector": [-87, 8, 0],
							"easing": "easeOutCubic"
						},
						"0.4167": {
							"vector": [-87, 8, 0],
							"easing": "easeOutCubic"
						},
						"0.5": {
							"vector": [-50, 19, 13],
							"easing": "linear"
						},
						"0.5833": {
							"vector": [-39, -12, -16],
							"easing": "easeInSine"
						},
						"0.625": {
							"vector": [0, -69, -45],
							"easing": "easeOutCubic"
						},
						"0.6667": {
							"vector": [0, -69, -45],
							"easing": "easeOutCubic"
						},
						"0.75": {
							"vector": [-23.10498, 1.95677, -26.31639],
							"easing": "linear"
						},
						"0.8333": {
							"vector": [-102, -75, 32],
							"easing": "easeInSine"
						},
						"0.875": {
							"vector": [-87, 8, 0],
							"easing": "easeOutCubic"
						},
						"0.9167": {
							"vector": [-87, 8, 0],
							"easing": "easeOutCubic"
						},
						"1.0": {
							"vector": [-50, 19, 13],
							"easing": "linear"
						},
						"1.0833": {
							"vector": [-39, -12, -16],
							"easing": "easeInSine"
						},
						"1.125": {
							"vector": [0, -69, -45],
							"easing": "easeOutCubic"
						},
						"1.1667": {
							"vector": [0, -69, -45],
							"easing": "easeOutCubic"
						},
						"1.25": {
							"vector": [-23.10498, 1.95677, -26.31639],
							"easing": "linear"
						},
						"1.3333": {
							"vector": [-102, -75, 32],
							"easing": "easeInSine"
						},
						"1.375": {
							"vector": [-87, 8, 0],
							"easing": "easeOutCubic"
						},
						"1.4167": {
							"vector": [-87, 8, 0],
							"easing": "easeOutCubic"
						},
						"1.5": {
							"vector": [-50, 19, 13],
							"easing": "linear"
						},
						"1.5833": {
							"vector": [-39, -12, -16],
							"easing": "easeInSine"
						},
						"1.625": {
							"vector": [0, -69, -45],
							"easing": "easeOutCubic"
						},
						"1.6667": {
							"vector": [0, -69, -45],
							"easing": "easeOutCubic"
						},
						"1.75": {
							"vector": [-23.10498, 1.95677, -26.31639],
							"easing": "linear"
						},
						"1.8333": {
							"vector": [-102, -75, 32],
							"easing": "easeInSine"
						},
						"1.875": {
							"vector": [-87, 8, 0],
							"easing": "easeOutCubic"
						},
						"1.9167": {
							"vector": [-87, 8, 0],
							"easing": "easeOutCubic"
						},
						"2.0": {
							"vector": [-50, 19, 13],
							"easing": "linear"
						},
						"2.0833": {
							"vector": [-39, -12, -16],
							"easing": "easeInSine"
						},
						"2.125": {
							"vector": [0, -69, -45],
							"easing": "easeOutCubic"
						},
						"2.1667": {
							"vector": [0, -69, -45],
							"easing": "easeOutCubic"
						},
						"2.25": {
							"vector": [-23.10498, 1.95677, -26.31639],
							"easing": "linear"
						},
						"2.3333": {
							"vector": [-102, -75, 32],
							"easing": "easeInSine"
						},
						"2.375": {
							"vector": [-87, 8, 0],
							"easing": "easeOutCubic"
						},
						"2.4167": {
							"vector": [-87, 8, 0],
							"easing": "easeOutCubic"
						},
						"2.5": {
							"vector": [-50, 19, 13],
							"easing": "linear"
						},
						"2.5833": {
							"vector": [-39, -12, -16],
							"easing": "easeInSine"
						},
						"2.625": {
							"vector": [0, -69, -45],
							"easing": "easeOutCubic"
						},
						"2.6667": {
							"vector": [0, -69, -45],
							"easing": "easeOutCubic"
						}
					},
					"position": {
						"0.0": {
							"vector": [1.75, -1.5, -5.75],
							"easing": "linear"
						},
						"0.0833": {
							"vector": [-2.5, -1.5, -9.75],
							"easing": "easeInSine"
						},
						"0.125": {
							"vector": [-2.5, -1.5, 5.25],
							"easing": "easeOutCubic"
						},
						"0.1667": {
							"vector": [-2.5, -1.5, 5.25],
							"easing": "easeOutCubic"
						},
						"0.25": {
							"vector": [-2, -2, 5],
							"easing": "linear"
						},
						"0.3333": {
							"vector": [-2, -2, 3],
							"easing": "easeInSine"
						},
						"0.375": {
							"vector": [-0.25, -0.75, -6],
							"easing": "easeOutCubic"
						},
						"0.4167": {
							"vector": [-0.25, -0.75, -6],
							"easing": "easeOutCubic"
						},
						"0.5": {
							"vector": [1.75, -1.5, -5.75],
							"easing": "linear"
						},
						"0.5833": {
							"vector": [-2.5, -1.5, -9.75],
							"easing": "easeInSine"
						},
						"0.625": {
							"vector": [-2.5, -1.5, 5.25],
							"easing": "easeOutCubic"
						},
						"0.6667": {
							"vector": [-2.5, -1.5, 5.25],
							"easing": "easeOutCubic"
						},
						"0.75": {
							"vector": [-2, -2, 5],
							"easing": "linear"
						},
						"0.8333": {
							"vector": [-2, -2, 3],
							"easing": "easeInSine"
						},
						"0.875": {
							"vector": [-0.25, -0.75, -6],
							"easing": "easeOutCubic"
						},
						"0.9167": {
							"vector": [-0.25, -0.75, -6],
							"easing": "easeOutCubic"
						},
						"1.0": {
							"vector": [1.75, -1.5, -5.75],
							"easing": "linear"
						},
						"1.0833": {
							"vector": [-2.5, -1.5, -9.75],
							"easing": "easeInSine"
						},
						"1.125": {
							"vector": [-2.5, -1.5, 5.25],
							"easing": "easeOutCubic"
						},
						"1.1667": {
							"vector": [-2.5, -1.5, 5.25],
							"easing": "easeOutCubic"
						},
						"1.25": {
							"vector": [-2, -2, 5],
							"easing": "linear"
						},
						"1.3333": {
							"vector": [-2, -2, 3],
							"easing": "easeInSine"
						},
						"1.375": {
							"vector": [-0.25, -0.75, -6],
							"easing": "easeOutCubic"
						},
						"1.4167": {
							"vector": [-0.25, -0.75, -6],
							"easing": "easeOutCubic"
						},
						"1.5": {
							"vector": [1.75, -1.5, -5.75],
							"easing": "linear"
						},
						"1.5833": {
							"vector": [-2.5, -1.5, -9.75],
							"easing": "easeInSine"
						},
						"1.625": {
							"vector": [-2.5, -1.5, 5.25],
							"easing": "easeOutCubic"
						},
						"1.6667": {
							"vector": [-2.5, -1.5, 5.25],
							"easing": "easeOutCubic"
						},
						"1.75": {
							"vector": [-2, -2, 5],
							"easing": "linear"
						},
						"1.8333": {
							"vector": [-2, -2, 3],
							"easing": "easeInSine"
						},
						"1.875": {
							"vector": [-0.25, -0.75, -6],
							"easing": "easeOutCubic"
						},
						"1.9167": {
							"vector": [-0.25, -0.75, -6],
							"easing": "easeOutCubic"
						},
						"2.0": {
							"vector": [1.75, -1.5, -5.75],
							"easing": "linear"
						},
						"2.0833": {
							"vector": [-2.5, -1.5, -9.75],
							"easing": "easeInSine"
						},
						"2.125": {
							"vector": [-2.5, -1.5, 5.25],
							"easing": "easeOutCubic"
						},
						"2.1667": {
							"vector": [-2.5, -1.5, 5.25],
							"easing": "easeOutCubic"
						},
						"2.25": {
							"vector": [-2, -2, 5],
							"easing": "linear"
						},
						"2.3333": {
							"vector": [-2, -2, 3],
							"easing": "easeInSine"
						},
						"2.375": {
							"vector": [-0.25, -0.75, -6],
							"easing": "easeOutCubic"
						},
						"2.4167": {
							"vector": [-0.25, -0.75, -6],
							"easing": "easeOutCubic"
						},
						"2.5": {
							"vector": [1.75, -1.5, -5.75],
							"easing": "linear"
						},
						"2.5833": {
							"vector": [-2.5, -1.5, -9.75],
							"easing": "easeInSine"
						},
						"2.625": {
							"vector": [-2.5, -1.5, 5.25],
							"easing": "easeOutCubic"
						},
						"2.6667": {
							"vector": [-2.5, -1.5, 5.25],
							"easing": "easeOutCubic"
						}
					}
				},
				"right_leg": {
					"rotation": {
						"0.0": {
							"vector": [24, 34, 14],
							"easing": "linear"
						},
						"0.0833": {
							"vector": [32, 25, 14],
							"easing": "easeInSine"
						},
						"0.125": {
							"vector": [32, 25, 14],
							"easing": "easeInSine"
						},
						"0.1667": {
							"vector": [32, 25, 14],
							"easing": "easeInSine"
						},
						"0.25": {
							"vector": [0, 0, 0]
						},
						"0.375": {
							"vector": [0, 0, 0]
						},
						"0.4167": {
							"vector": [0, 0, 0]
						},
						"0.5": {
							"vector": [24, 34, 14],
							"easing": "linear"
						},
						"0.5833": {
							"vector": [32, 25, 14],
							"easing": "easeInSine"
						},
						"0.625": {
							"vector": [32, 25, 14],
							"easing": "easeInSine"
						},
						"0.6667": {
							"vector": [32, 25, 14],
							"easing": "easeInSine"
						},
						"0.75": {
							"vector": [0, 0, 0]
						},
						"0.875": {
							"vector": [0, 0, 0]
						},
						"0.9167": {
							"vector": [0, 0, 0]
						},
						"1.0": {
							"vector": [24, 34, 14],
							"easing": "linear"
						},
						"1.0833": {
							"vector": [32, 25, 14],
							"easing": "easeInSine"
						},
						"1.125": {
							"vector": [32, 25, 14],
							"easing": "easeInSine"
						},
						"1.1667": {
							"vector": [32, 25, 14],
							"easing": "easeInSine"
						},
						"1.25": {
							"vector": [0, 0, 0]
						},
						"1.375": {
							"vector": [0, 0, 0]
						},
						"1.4167": {
							"vector": [0, 0, 0]
						},
						"1.5": {
							"vector": [24, 34, 14],
							"easing": "linear"
						},
						"1.5833": {
							"vector": [32, 25, 14],
							"easing": "easeInSine"
						},
						"1.625": {
							"vector": [32, 25, 14],
							"easing": "easeInSine"
						},
						"1.6667": {
							"vector": [32, 25, 14],
							"easing": "easeInSine"
						},
						"1.75": {
							"vector": [0, 0, 0]
						},
						"1.875": {
							"vector": [0, 0, 0]
						},
						"1.9167": {
							"vector": [0, 0, 0]
						},
						"2.0": {
							"vector": [24, 34, 14],
							"easing": "linear"
						},
						"2.0833": {
							"vector": [32, 25, 14],
							"easing": "easeInSine"
						},
						"2.125": {
							"vector": [32, 25, 14],
							"easing": "easeInSine"
						},
						"2.1667": {
							"vector": [32, 25, 14],
							"easing": "easeInSine"
						},
						"2.25": {
							"vector": [0, 0, 0]
						},
						"2.375": {
							"vector": [0, 0, 0]
						},
						"2.4167": {
							"vector": [0, 0, 0]
						},
						"2.5": {
							"vector": [24, 34, 14],
							"easing": "linear"
						},
						"2.5833": {
							"vector": [32, 25, 14],
							"easing": "easeInSine"
						},
						"2.625": {
							"vector": [32, 25, 14],
							"easing": "easeInSine"
						},
						"2.6667": {
							"vector": [32, 25, 14],
							"easing": "easeInSine"
						}
					},
					"position": {
						"0.0": {
							"vector": [0, 0, 3],
							"easing": "linear"
						},
						"0.0833": {
							"vector": [0, 0, 3],
							"easing": "easeInSine"
						},
						"0.125": {
							"vector": [-1.5, 0, 2.75],
							"easing": "easeOutCubic"
						},
						"0.1667": {
							"vector": [-1.5, 0, 2.75],
							"easing": "easeOutCubic"
						},
						"0.25": {
							"vector": [-1, 0, -2],
							"easing": "linear"
						},
						"0.3333": {
							"vector": [-1, 0, -2.75],
							"easing": "easeInSine"
						},
						"0.375": {
							"vector": [-1, 0, -3.25],
							"easing": "easeOutCubic"
						},
						"0.4167": {
							"vector": [-1, 0, -3.25],
							"easing": "easeOutCubic"
						},
						"0.5": {
							"vector": [0, 0, 3],
							"easing": "linear"
						},
						"0.5833": {
							"vector": [0, 0, 3],
							"easing": "easeInSine"
						},
						"0.625": {
							"vector": [-1.5, 0, 2.75],
							"easing": "easeOutCubic"
						},
						"0.6667": {
							"vector": [-1.5, 0, 2.75],
							"easing": "easeOutCubic"
						},
						"0.75": {
							"vector": [-1, 0, -2],
							"easing": "linear"
						},
						"0.8333": {
							"vector": [-1, 0, -2.75],
							"easing": "easeInSine"
						},
						"0.875": {
							"vector": [-1, 0, -3.25],
							"easing": "easeOutCubic"
						},
						"0.9167": {
							"vector": [-1, 0, -3.25],
							"easing": "easeOutCubic"
						},
						"1.0": {
							"vector": [0, 0, 3],
							"easing": "linear"
						},
						"1.0833": {
							"vector": [0, 0, 3],
							"easing": "easeInSine"
						},
						"1.125": {
							"vector": [-1.5, 0, 2.75],
							"easing": "easeOutCubic"
						},
						"1.1667": {
							"vector": [-1.5, 0, 2.75],
							"easing": "easeOutCubic"
						},
						"1.25": {
							"vector": [-1, 0, -2],
							"easing": "linear"
						},
						"1.3333": {
							"vector": [-1, 0, -2.75],
							"easing": "easeInSine"
						},
						"1.375": {
							"vector": [-1, 0, -3.25],
							"easing": "easeOutCubic"
						},
						"1.4167": {
							"vector": [-1, 0, -3.25],
							"easing": "easeOutCubic"
						},
						"1.5": {
							"vector": [0, 0, 3],
							"easing": "linear"
						},
						"1.5833": {
							"vector": [0, 0, 3],
							"easing": "easeInSine"
						},
						"1.625": {
							"vector": [-1.5, 0, 2.75],
							"easing": "easeOutCubic"
						},
						"1.6667": {
							"vector": [-1.5, 0, 2.75],
							"easing": "easeOutCubic"
						},
						"1.75": {
							"vector": [-1, 0, -2],
							"easing": "linear"
						},
						"1.8333": {
							"vector": [-1, 0, -2.75],
							"easing": "easeInSine"
						},
						"1.875": {
							"vector": [-1, 0, -3.25],
							"easing": "easeOutCubic"
						},
						"1.9167": {
							"vector": [-1, 0, -3.25],
							"easing": "easeOutCubic"
						},
						"2.0": {
							"vector": [0, 0, 3],
							"easing": "linear"
						},
						"2.0833": {
							"vector": [0, 0, 3],
							"easing": "easeInSine"
						},
						"2.125": {
							"vector": [-1.5, 0, 2.75],
							"easing": "easeOutCubic"
						},
						"2.1667": {
							"vector": [-1.5, 0, 2.75],
							"easing": "easeOutCubic"
						},
						"2.25": {
							"vector": [-1, 0, -2],
							"easing": "linear"
						},
						"2.3333": {
							"vector": [-1, 0, -2.75],
							"easing": "easeInSine"
						},
						"2.375": {
							"vector": [-1, 0, -3.25],
							"easing": "easeOutCubic"
						},
						"2.4167": {
							"vector": [-1, 0, -3.25],
							"easing": "easeOutCubic"
						},
						"2.5": {
							"vector": [0, 0, 3],
							"easing": "linear"
						},
						"2.5833": {
							"vector": [0, 0, 3],
							"easing": "easeInSine"
						},
						"2.625": {
							"vector": [-1.5, 0, 2.75],
							"easing": "easeOutCubic"
						},
						"2.6667": {
							"vector": [-1.5, 0, 2.75],
							"easing": "easeOutCubic"
						}
					}
				},
				"left_leg": {
					"rotation": {
						"0.0": {
							"vector": [2.6, 2.3, 2],
							"easing": "linear"
						},
						"0.125": {
							"vector": [2.6, 2.3, 2],
							"easing": "linear"
						},
						"0.1667": {
							"vector": [2.6, 2.3, 2],
							"easing": "linear"
						},
						"0.25": {
							"vector": [24, -34, -14],
							"easing": "linear"
						},
						"0.375": {
							"vector": [24, -34, -14],
							"easing": "linear"
						},
						"0.4167": {
							"vector": [24, -34, -14],
							"easing": "linear"
						},
						"0.5": {
							"vector": [2.6, 2.3, 2],
							"easing": "linear"
						},
						"0.625": {
							"vector": [2.6, 2.3, 2],
							"easing": "linear"
						},
						"0.6667": {
							"vector": [2.6, 2.3, 2],
							"easing": "linear"
						},
						"0.75": {
							"vector": [24, -34, -14],
							"easing": "linear"
						},
						"0.875": {
							"vector": [24, -34, -14],
							"easing": "linear"
						},
						"0.9167": {
							"vector": [24, -34, -14],
							"easing": "linear"
						},
						"1.0": {
							"vector": [2.6, 2.3, 2],
							"easing": "linear"
						},
						"1.125": {
							"vector": [2.6, 2.3, 2],
							"easing": "linear"
						},
						"1.1667": {
							"vector": [2.6, 2.3, 2],
							"easing": "linear"
						},
						"1.25": {
							"vector": [24, -34, -14],
							"easing": "linear"
						},
						"1.375": {
							"vector": [24, -34, -14],
							"easing": "linear"
						},
						"1.4167": {
							"vector": [24, -34, -14],
							"easing": "linear"
						},
						"1.5": {
							"vector": [2.6, 2.3, 2],
							"easing": "linear"
						},
						"1.625": {
							"vector": [2.6, 2.3, 2],
							"easing": "linear"
						},
						"1.6667": {
							"vector": [2.6, 2.3, 2],
							"easing": "linear"
						},
						"1.75": {
							"vector": [24, -34, -14],
							"easing": "linear"
						},
						"1.875": {
							"vector": [24, -34, -14],
							"easing": "linear"
						},
						"1.9167": {
							"vector": [24, -34, -14],
							"easing": "linear"
						},
						"2.0": {
							"vector": [2.6, 2.3, 2],
							"easing": "linear"
						},
						"2.125": {
							"vector": [2.6, 2.3, 2],
							"easing": "linear"
						},
						"2.1667": {
							"vector": [2.6, 2.3, 2],
							"easing": "linear"
						},
						"2.25": {
							"vector": [24, -34, -14],
							"easing": "linear"
						},
						"2.375": {
							"vector": [24, -34, -14],
							"easing": "linear"
						},
						"2.4167": {
							"vector": [24, -34, -14],
							"easing": "linear"
						},
						"2.5": {
							"vector": [2.6, 2.3, 2],
							"easing": "linear"
						},
						"2.625": {
							"vector": [2.6, 2.3, 2],
							"easing": "linear"
						},
						"2.6667": {
							"vector": [2.6, 2.3, 2],
							"easing": "linear"
						}
					},
					"position": {
						"0.0": {
							"vector": [1, 0, -2],
							"easing": "linear"
						},
						"0.0833": {
							"vector": [1, 0, -2.75],
							"easing": "easeInSine"
						},
						"0.125": {
							"vector": [1, 0, -3.25],
							"easing": "easeOutCubic"
						},
						"0.1667": {
							"vector": [1, 0, -3.25],
							"easing": "easeOutCubic"
						},
						"0.25": {
							"vector": [0, 0, 3],
							"easing": "linear"
						},
						"0.3333": {
							"vector": [0, 0, 3],
							"easing": "easeInSine"
						},
						"0.375": {
							"vector": [1.5, 0, 2.75],
							"easing": "easeOutCubic"
						},
						"0.4167": {
							"vector": [1.5, 0, 2.75],
							"easing": "easeOutCubic"
						},
						"0.5": {
							"vector": [1, 0, -2],
							"easing": "linear"
						},
						"0.5833": {
							"vector": [1, 0, -2.75],
							"easing": "easeInSine"
						},
						"0.625": {
							"vector": [1, 0, -3.25],
							"easing": "easeOutCubic"
						},
						"0.6667": {
							"vector": [1, 0, -3.25],
							"easing": "easeOutCubic"
						},
						"0.75": {
							"vector": [0, 0, 3],
							"easing": "linear"
						},
						"0.8333": {
							"vector": [0, 0, 3],
							"easing": "easeInSine"
						},
						"0.875": {
							"vector": [1.5, 0, 2.75],
							"easing": "easeOutCubic"
						},
						"0.9167": {
							"vector": [1.5, 0, 2.75],
							"easing": "easeOutCubic"
						},
						"1.0": {
							"vector": [1, 0, -2],
							"easing": "linear"
						},
						"1.0833": {
							"vector": [1, 0, -2.75],
							"easing": "easeInSine"
						},
						"1.125": {
							"vector": [1, 0, -3.25],
							"easing": "easeOutCubic"
						},
						"1.1667": {
							"vector": [1, 0, -3.25],
							"easing": "easeOutCubic"
						},
						"1.25": {
							"vector": [0, 0, 3],
							"easing": "linear"
						},
						"1.3333": {
							"vector": [0, 0, 3],
							"easing": "easeInSine"
						},
						"1.375": {
							"vector": [1.5, 0, 2.75],
							"easing": "easeOutCubic"
						},
						"1.4167": {
							"vector": [1.5, 0, 2.75],
							"easing": "easeOutCubic"
						},
						"1.5": {
							"vector": [1, 0, -2],
							"easing": "linear"
						},
						"1.5833": {
							"vector": [1, 0, -2.75],
							"easing": "easeInSine"
						},
						"1.625": {
							"vector": [1, 0, -3.25],
							"easing": "easeOutCubic"
						},
						"1.6667": {
							"vector": [1, 0, -3.25],
							"easing": "easeOutCubic"
						},
						"1.75": {
							"vector": [0, 0, 3],
							"easing": "linear"
						},
						"1.8333": {
							"vector": [0, 0, 3],
							"easing": "easeInSine"
						},
						"1.875": {
							"vector": [1.5, 0, 2.75],
							"easing": "easeOutCubic"
						},
						"1.9167": {
							"vector": [1.5, 0, 2.75],
							"easing": "easeOutCubic"
						},
						"2.0": {
							"vector": [1, 0, -2],
							"easing": "linear"
						},
						"2.0833": {
							"vector": [1, 0, -2.75],
							"easing": "easeInSine"
						},
						"2.125": {
							"vector": [1, 0, -3.25],
							"easing": "easeOutCubic"
						},
						"2.1667": {
							"vector": [1, 0, -3.25],
							"easing": "easeOutCubic"
						},
						"2.25": {
							"vector": [0, 0, 3],
							"easing": "linear"
						},
						"2.3333": {
							"vector": [0, 0, 3],
							"easing": "easeInSine"
						},
						"2.375": {
							"vector": [1.5, 0, 2.75],
							"easing": "easeOutCubic"
						},
						"2.4167": {
							"vector": [1.5, 0, 2.75],
							"easing": "easeOutCubic"
						},
						"2.5": {
							"vector": [1, 0, -2],
							"easing": "linear"
						},
						"2.5833": {
							"vector": [1, 0, -2.75],
							"easing": "easeInSine"
						},
						"2.625": {
							"vector": [1, 0, -3.25],
							"easing": "easeOutCubic"
						},
						"2.6667": {
							"vector": [1, 0, -3.25],
							"easing": "easeOutCubic"
						}
					}
				},
				"boobies": {
					"position": {
						"0.0": {
							"vector": [0, 0, 0]
						},
						"0.0833": {
							"vector": [-0.25, -0.5, -0.25],
							"easing": "easeOutBack",
							"easingArgs": [3]
						},
						"0.125": {
							"vector": [0.54, 0.89, -0.25],
							"easing": "easeOutBack",
							"easingArgs": [3]
						},
						"0.1667": {
							"vector": [0, 0.5, -0.25],
							"easing": "easeOutBack",
							"easingArgs": [3]
						},
						"0.25": {
							"vector": [0, 0, 0]
						},
						"0.3333": {
							"vector": [-0.25, -0.5, -0.25],
							"easing": "easeOutBack",
							"easingArgs": [3]
						},
						"0.375": {
							"vector": [0.54, 0.89, -0.25],
							"easing": "easeOutBack",
							"easingArgs": [3]
						},
						"0.4167": {
							"vector": [0, 0.5, -0.25],
							"easing": "easeOutBack",
							"easingArgs": [3]
						},
						"0.5": {
							"vector": [0, 0, 0]
						},
						"0.5833": {
							"vector": [-0.25, -0.5, -0.25],
							"easing": "easeOutBack",
							"easingArgs": [3]
						},
						"0.625": {
							"vector": [0.54, 0.89, -0.25],
							"easing": "easeOutBack",
							"easingArgs": [3]
						},
						"0.6667": {
							"vector": [0, 0.5, -0.25],
							"easing": "easeOutBack",
							"easingArgs": [3]
						},
						"0.75": {
							"vector": [0, 0, 0]
						},
						"0.8333": {
							"vector": [-0.25, -0.5, -0.25],
							"easing": "easeOutBack",
							"easingArgs": [3]
						},
						"0.875": {
							"vector": [0.54, 0.89, -0.25],
							"easing": "easeOutBack",
							"easingArgs": [3]
						},
						"0.9167": {
							"vector": [0, 0.5, -0.25],
							"easing": "easeOutBack",
							"easingArgs": [3]
						},
						"1.0": {
							"vector": [0, 0, 0]
						},
						"1.0833": {
							"vector": [-0.25, -0.5, -0.25],
							"easing": "easeOutBack",
							"easingArgs": [3]
						},
						"1.125": {
							"vector": [0.54, 0.89, -0.25],
							"easing": "easeOutBack",
							"easingArgs": [3]
						},
						"1.1667": {
							"vector": [0, 0.5, -0.25],
							"easing": "easeOutBack",
							"easingArgs": [3]
						},
						"1.25": {
							"vector": [0, 0, 0]
						},
						"1.3333": {
							"vector": [-0.25, -0.5, -0.25],
							"easing": "easeOutBack",
							"easingArgs": [3]
						},
						"1.375": {
							"vector": [0.54, 0.89, -0.25],
							"easing": "easeOutBack",
							"easingArgs": [3]
						},
						"1.4167": {
							"vector": [0, 0.5, -0.25],
							"easing": "easeOutBack",
							"easingArgs": [3]
						},
						"1.5": {
							"vector": [0, 0, 0]
						},
						"1.5833": {
							"vector": [-0.25, -0.5, -0.25],
							"easing": "easeOutBack",
							"easingArgs": [3]
						},
						"1.625": {
							"vector": [0.54, 0.89, -0.25],
							"easing": "easeOutBack",
							"easingArgs": [3]
						},
						"1.6667": {
							"vector": [0, 0.5, -0.25],
							"easing": "easeOutBack",
							"easingArgs": [3]
						},
						"1.75": {
							"vector": [0, 0, 0]
						},
						"1.8333": {
							"vector": [-0.25, -0.5, -0.25],
							"easing": "easeOutBack",
							"easingArgs": [3]
						},
						"1.875": {
							"vector": [0.54, 0.89, -0.25],
							"easing": "easeOutBack",
							"easingArgs": [3]
						},
						"1.9167": {
							"vector": [0, 0.5, -0.25],
							"easing": "easeOutBack",
							"easingArgs": [3]
						},
						"2.0": {
							"vector": [0, 0, 0]
						},
						"2.0833": {
							"vector": [-0.25, -0.5, -0.25],
							"easing": "easeOutBack",
							"easingArgs": [3]
						},
						"2.125": {
							"vector": [0.54, 0.89, -0.25],
							"easing": "easeOutBack",
							"easingArgs": [3]
						},
						"2.1667": {
							"vector": [0, 0.5, -0.25],
							"easing": "easeOutBack",
							"easingArgs": [3]
						},
						"2.25": {
							"vector": [0, 0, 0]
						},
						"2.3333": {
							"vector": [-0.25, -0.5, -0.25],
							"easing": "easeOutBack",
							"easingArgs": [3]
						},
						"2.375": {
							"vector": [0.54, 0.89, -0.25],
							"easing": "easeOutBack",
							"easingArgs": [3]
						},
						"2.4167": {
							"vector": [0, 0.5, -0.25],
							"easing": "easeOutBack",
							"easingArgs": [3]
						},
						"2.5": {
							"vector": [0, 0, 0]
						},
						"2.5833": {
							"vector": [0, 0.5, -0.25],
							"easing": "easeOutBack",
							"easingArgs": [3]
						},
						"2.75": {
							"vector": [0, 0, 0],
							"easing": "easeOutBack",
							"easingArgs": [3]
						},
						"2.875": {
							"vector": [0, 0.25, -0.15],
							"easing": "easeOutBack",
							"easingArgs": [3]
						},
						"3.0417": {
							"vector": [0, 0, 0],
							"easing": "easeOutBack",
							"easingArgs": [3]
						}
					}
				}
			}
		},
		"upslam": {
			"animation_length": 0.5833,
			"bones": {
				"body": {
					"rotation": {
						"0.0": {
							"vector": [0, 0, 0]
						},
						"0.4167": {
							"vector": [2.00307, 14.8687, 7.7614]
						}
					}
				},
				"head": {
					"rotation": {
						"0.0": {
							"vector": [14, 24, -2]
						},
						"0.125": {
							"vector": [8, 14, -10]
						},
						"0.2083": {
							"vector": [-8.5, -19.5, 9]
						}
					},
					"position": {
						"0.0": {
							"vector": [1.75, -0.75, -2.5]
						},
						"0.125": {
							"vector": [-2, -0.75, -4]
						},
						"0.2083": {
							"vector": [2.5, -0.75, -3.5]
						}
					}
				},
				"torso": {
					"rotation": {
						"0.0": {
							"vector": [27, 30, 10]
						},
						"0.125": {
							"vector": [21, 44, -4]
						},
						"0.2083": {
							"vector": [28, -42.5, -5.5]
						}
					},
					"position": {
						"0.0": {
							"vector": [1.75, -1, -2]
						},
						"0.125": {
							"vector": [-2, -1, -4]
						},
						"0.2083": {
							"vector": [1.75, -0.25, -2.75]
						}
					}
				},
				"right_arm": {
					"rotation": {
						"0.0": {
							"vector": [-23.10498, -1.95677, 26.31639]
						},
						"0.125": {
							"vector": [-65, 75, -32]
						},
						"0.2083": {
							"vector": [-127, -8, 0]
						},
						"0.4583": {
							"vector": [-136, 2, 0]
						}
					},
					"position": {
						"0.0": {
							"vector": [2, -2, 5]
						},
						"0.125": {
							"vector": [2, -2, 3]
						},
						"0.2083": {
							"vector": [1, 2, -7]
						},
						"0.4583": {
							"vector": [1.5, 2, -8.5]
						}
					}
				},
				"left_arm": {
					"rotation": {
						"0.0": {
							"vector": [-50, 19, 13]
						},
						"0.125": {
							"vector": [-74, -2.5, -13]
						},
						"0.2083": {
							"vector": [-50, -56, 10]
						},
						"0.4583": {
							"vector": [-149.5, -33, 25]
						}
					},
					"position": {
						"0.0": {
							"vector": [1.75, -1.5, -5.75]
						},
						"0.125": {
							"vector": [-2.5, -1.5, -9.75]
						},
						"0.2083": {
							"vector": [-2.5, -1.5, 5.25]
						},
						"0.4583": {
							"vector": [-1.25, -6, 4.25]
						}
					}
				},
				"right_leg": {
					"rotation": {
						"0.0": {
							"vector": [24, 34, 14]
						},
						"0.125": {
							"vector": [32, 25, 14.5]
						},
						"0.2083": {
							"vector": [30, -27.5, 6]
						}
					},
					"position": {
						"0.0": {
							"vector": [0, 0, 3]
						},
						"0.125": {
							"vector": [0, 0, 3.75]
						},
						"0.2083": {
							"vector": [-1, 0.75, 0.25]
						}
					}
				},
				"left_leg": {
					"rotation": {
						"0.0": {
							"vector": [2.6, 2.3, 2]
						},
						"0.125": {
							"vector": [2.6, 2.3, 2]
						},
						"0.2083": {
							"vector": [48, -30, -2]
						}
					},
					"position": {
						"0.0": {
							"vector": [1, 0, -2]
						},
						"0.125": {
							"vector": [1, 0, -2.75]
						},
						"0.2083": {
							"vector": [2.75, 1.5, -3.25]
						}
					}
				}
			}
		},
		"targeting": {
			"animation_length": 0.25,
			"bones": {
				"head": {
					"rotation": {
						"vector": [-10, 0, 0]
					},
					"position": {
						"vector": [0, 1, 0]
					}
				},
				"torso": {
					"rotation": {
						"vector": [7.56, 7.44, 0.98]
					},
					"position": {
						"vector": [0, 1, 0]
					}
				},
				"right_arm": {
					"rotation": {
						"vector": [23.30696, -9.30727, 10.57639]
					}
				},
				"left_arm": {
					"rotation": {
						"vector": [-9.99, -0.22, -10]
					},
					"position": {
						"vector": [0, 0, 0]
					}
				},
				"right_leg": {
					"rotation": {
						"vector": [22.5, 5, 0]
					},
					"position": {
						"vector": [0, 3, -2]
					}
				},
				"left_leg": {
					"rotation": {
						"vector": [9.89, -7.5, 2.51]
					},
					"position": {
						"vector": [0, 1, 0]
					}
				},
				"body": {
					"rotation": {
						"vector": [12.5, 0, 0]
					}
				}
			}
		}
	},
	"geckolib_format_version": 2
}